MANIFEST.in
account_invoice_view.xml
partner_view.xml
setup.py
./__init__.py
./__openerp__.py
./invoice.py
./partner.py
i18n/ar.po
i18n/es.po
i18n/es_CR.po
i18n/fr.po
i18n/l10n_be_invoice_bba.pot
i18n/nb.po
i18n/nl.po
i18n/nl_BE.po
i18n/pt.po
i18n/pt_BR.po
i18n/sl.po
i18n/sr@latin.po
i18n/tr.po
openerp_l10n_be_invoice_bba.egg-info/PKG-INFO
openerp_l10n_be_invoice_bba.egg-info/SOURCES.txt
openerp_l10n_be_invoice_bba.egg-info/dependency_links.txt
openerp_l10n_be_invoice_bba.egg-info/requires.txt
openerp_l10n_be_invoice_bba.egg-info/top_level.txt